{
  "initialScreen": {
    "backgroundEndColor": "#14477d",
    "backgroundStartColor": "#1b75bc",
    "decorativeDiamonds": [
      {
        "borderColor": "rgba(237,237,237,0.25)",
        "height": 360,
        "left": 460,
        "opacity": 1,
        "top": 1870,
        "width": 360
      },
      {
        "borderColor": "rgba(237,237,237,0.25)",
        "height": 520,
        "left": 680,
        "opacity": 1,
        "top": 2100,
        "width": 520
      },
      {
        "fillColor": "#f26522",
        "height": 140,
        "left": 520,
        "opacity": 1,
        "top": 2250,
        "width": 140
      }
    ],
    "eyebrow": ["Rich media &", "cultural heritage"],
    "headline": ["Learn more about how we unlocked new possibilities", "for our partners"],
    "heroImageAlt": "Visitors review digital media inside the Grammy Museum",
    "heroImageSrc": "",
    "primaryCtaLabel": "From archive to access",
    "saveForLaterLabel": "Save for later",
    "secondaryCtaLabel": "Virtual walkthrough"
  },
  "firstScreen": {
    "backCtaLabel": "Back to menu",
    "backgroundEndColor": "#0a2f5c",
    "backgroundStartColor": "#1b75bc",
    "description": "Explore each section to learn how Iron Mountain can transform your enterprise",
    "eyebrow": ["Rich media &", "cultural heritage"],
    "headline": "From archive to access",
    "slides": [
      {
        "id": "intake",
        "title": "Intake",
        "subtitle": "and assessment"
      },
      {
        "id": "digitization",
        "title": "Digitization",
        "subtitle": "and remediation"
      },
      {
        "highlight": true,
        "id": "preservation",
        "title": "Digital",
        "subtitle": "Preservation"
      },
      {
        "id": "search",
        "title": "Search and",
        "subtitle": "discover"
      },
      {
        "id": "share",
        "title": "Share, stream",
        "subtitle": "and monetize"
      }
    ]
  },
  "secondScreens": [
    {
      "backLabel": "Back",
      "backgroundImageSrc": "",
      "description": [
        "Assets, whether film, audio, digital, or physical, are logged, evaluated for condition and risk,",
        "and prioritized based on preservation and activation potential."
      ],
      "eyebrow": ["Rich media &", "cultural heritage"],
      "headline": "Intake and assessment",
      "iconImageAlt": "Logbook and film reel",
      "iconImageSrc": "",
      "panelBackgroundColor": "#6dcff6"
    },
    {
      "backLabel": "Back",
      "backgroundImageSrc": "",
      "description": [
        "Every handoff is captured with digital chain-of-custody signatures,",
        "providing real-time transparency across museums, archives, and Iron Mountain vaults."
      ],
      "eyebrow": ["Rich media &", "cultural heritage"],
      "headline": "Chain-of-custody visibility",
      "iconImageAlt": "Chain of custody visualization",
      "iconImageSrc": "",
      "panelBackgroundColor": "#67d6ff"
    },
    {
      "backLabel": "Back",
      "backgroundImageSrc": "",
      "description": [
        "Materials are stabilized, humidity-controlled, and cataloged with preservation notes",
        "so curators can understand risk and readiness before activation."
      ],
      "eyebrow": ["Rich media &", "cultural heritage"],
      "headline": "Preservation readiness",
      "iconImageAlt": "Preservation environment graphic",
      "iconImageSrc": "",
      "panelBackgroundColor": "#6ac5f8"
    },
    {
      "backLabel": "Back",
      "backgroundImageSrc": "",
      "description": [
        "Sensors monitor temperature, vibration, and light exposure with automated alerts,",
        "ensuring priceless artifacts stay within safe tolerances."
      ],
      "eyebrow": ["Rich media &", "cultural heritage"],
      "headline": "Environmental monitoring",
      "iconImageAlt": "Sensor dashboard illustration",
      "iconImageSrc": "",
      "panelBackgroundColor": "#5ec0f2"
    },
    {
      "backLabel": "Back",
      "backgroundImageSrc": "",
      "description": [
        "Curators select highlight reels, transcripts, and metadata bundles",
        "to accelerate publishing across galleries, education partners, and streaming endpoints."
      ],
      "eyebrow": ["Rich media &", "cultural heritage"],
      "headline": "Activation planning",
      "iconImageAlt": "Activation planning icon",
      "iconImageSrc": "",
      "panelBackgroundColor": "#58b9eb"
    }
  ],
  "thirdScreen": {
    "backgroundEndColor": "#05254b",
    "backgroundStartColor": "#1b75bc",
    "cardBackgroundColor": "#e0e0e0",
    "cardLabel": "Virtual walkthrough",
    "cardTextColor": "#4a4a4a",
    "headline": ["Section title lorem ipsum", "dolor sit."]
  }
}
